volcengine/ApiInfo.py
volcengine/Credentials.py
volcengine/Policy.py
volcengine/ServiceInfo.py
volcengine/ServiceInfoHttps.py
volcengine/__init__.py
volcengine/adblocker/AdBlockerService.py
volcengine/adblocker/__init__.py
volcengine/auth/MetaData.py
volcengine/auth/SignParam.py
volcengine/auth/SignResult.py
volcengine/auth/SignerV4.py
volcengine/auth/__init__.py
volcengine/base/Request.py
volcengine/base/Service.py
volcengine/base/__init__.py
volcengine/base/models/__init__.py
volcengine/base/models/base/__init__.py
volcengine/base/models/base/base_pb2.py
volcengine/base/models/business/VQScore_pb2.py
volcengine/base/models/business/__init__.py
volcengine/base/models/business/addr_pb2.py
volcengine/base/models/business/deny_config_pb2.py
volcengine/base/models/business/domain_pb2.py
volcengine/base/models/business/pull_to_push_pb2.py
volcengine/base/models/business/record_manage_pb2.py
volcengine/base/models/business/relay_source_pb2.py
volcengine/base/models/business/snapshot_manage_pb2.py
volcengine/base/models/business/stream_manage_pb2.py
volcengine/billing/BillingService.py
volcengine/billing/__init__.py
volcengine/bioos/BioOsService.py
volcengine/bioos/__init__.py
volcengine/bioos/doc/__init__.py
volcengine/bioos/doc/source/__init__.py
volcengine/bioos/doc/source/conf.py
volcengine/business_security/RiskDetectionService.py
volcengine/business_security/__init__.py
volcengine/cdn/__init__.py
volcengine/cdn/service.py
volcengine/code_pipeline/CodePipelineService.py
volcengine/code_pipeline/__init__.py
volcengine/const/Const.py
volcengine/const/__init__.py
volcengine/content_security/ContentSecurityService.py
volcengine/content_security/RcLlmAgentService.py
volcengine/content_security/__init__.py
volcengine/dcdn/DCDNService.py
volcengine/dcdn/__init__.py
volcengine/dts/__init__.py
volcengine/dts/dts_service.py
volcengine/emr/EMRService.py
volcengine/emr/__init__.py
volcengine/example/DemoSignOnly.py
volcengine/example/__init__.py
volcengine-1.0.215.dist-info/LICENSE
volcengine-1.0.215.dist-info/METADATA
volcengine-1.0.215.dist-info/WHEEL
volcengine-1.0.215.dist-info/top_level.txt
volcengine-1.0.215.dist-info/RECORD
